stadata/__init__.py
stadata/main.py
stadata/material.py
stadata-1.0.0.dist-info/METADATA
stadata-1.0.0.dist-info/WHEEL
stadata-1.0.0.dist-info/RECORD
